<Properties StartupConfiguration="{45E2CE63-B5BD-4C6A-962A-E249371F6A70}|Default">
  <MonoDevelop.Ide.Workbench ActiveDocument="Pages/Movies/Details.cshtml.cs">
    <Files>
      <File FileName="Models/Movie.cs" Line="18" Column="11" />
      <File FileName="Models/RazorPagesMovieContext.cs" Line="18" Column="1" />
      <File FileName="appsettings.json" Line="10" Column="3" />
      <File FileName="README.md" Line="5" Column="19" />
      <File FileName="Startup.cs" Line="27" Column="38" />
      <File FileName="Pages/Movies/Index.cshtml.cs" Line="20" Column="1" />
      <File FileName="Pages/Movies/Index.cshtml" Line="2" Column="7" />
      <File FileName="Pages/Shared/_Layout.cshtml" Line="9" Column="56" />
      <File FileName="Program.cs" Line="30" Column="82" />
      <File FileName="Models/SeedData.cs" Line="17" Column="20" />
      <File FileName="Pages/Movies/Details.cshtml.cs" Line="23" Column="1" />
    </Files>
    <Pads>
      <Pad Id="ProjectPad">
        <State name="__root__">
          <Node name="RazorPagesMovie" expanded="True">
            <Node name="RazorPagesMovie" expanded="True">
              <Node name="Models" expanded="True" />
              <Node name="Pages" expanded="True">
                <Node name="Movies" expanded="True">
                  <Node name="Details.cshtml.cs" selected="True" />
                </Node>
              </Node>
            </Node>
          </Node>
        </State>
      </Pad>
    </Pads>
  </MonoDevelop.Ide.Workbench>
  <MonoDevelop.Ide.DebuggingService.PinnedWatches />
  <MonoDevelop.Ide.ItemProperties.RazorPagesMovie PreferredExecutionTarget="MonoDevelop.Default" />
  <MonoDevelop.Ide.Workspace ActiveConfiguration="Debug" />
  <MonoDevelop.Ide.DebuggingService.Breakpoints>
    <BreakpointStore />
  </MonoDevelop.Ide.DebuggingService.Breakpoints>
  <MultiItemStartupConfigurations />
</Properties>